[{"user": "user2", "created_at": 1454893181.0, "name": "Data Collection", "due_at": null, "closed_at": 1456708047.0, "description": "Create the server in MEAN and pull all the needed data from stackoverflow.", "id": 1569204, "number": 2}, {"user": "user2", "created_at": 1456464113.0, "name": "Front End", "due_at": null, "closed_at": 1456708050.0, "description": "Front end using a browser! Offline handling using a node.js server!", "id": 1607423, "number": 6}, {"user": "user2", "created_at": 1456191813.0, "name": "Basic analysis algorithm 1", "due_at": 1456635600.0, "closed_at": 1456708058.0, "description": "Implement one of the analysis algorithms and make it ready for integration in the plugin.", "id": 1598816, "number": 5}, {"user": "user2", "created_at": 1454893683.0, "name": "Text Mining using NLTK", "due_at": 1456635600.0, "closed_at": 1456708061.0, "description": "Get the text mining part i.e. the recommendation system working for use by the plugin.", "id": 1569209, "number": 3}, {"user": "user2", "created_at": 1454893762.0, "name": "Creating the Plugin that uses the Recommendation System", "due_at": 1456722000.0, "closed_at": 1456708062.0, "description": "Create the final plugin that uses the recommendation system built using NLTK in python.", "id": 1569212, "number": 4}, {"user": "user2", "created_at": 1456707991.0, "name": "Solution #1", "due_at": 1456808400.0, "closed_at": 1460088125.0, "description": "Solution 1 for the recommendation system!", "id": 1610699, "number": 7}, {"user": "user2", "created_at": 1456708079.0, "name": "Solution #2", "due_at": 1456808400.0, "closed_at": 1460088127.0, "description": "implementing solution #2", "id": 1610704, "number": 8}, {"user": "user2", "created_at": 1456708099.0, "name": "Solution #3", "due_at": 1456808400.0, "closed_at": 1460088126.0, "description": "Think and decide and then implement solution #3", "id": 1610705, "number": 9}, {"user": "user2", "created_at": 1460697097.0, "name": "Project 2 - Data Collection", "due_at": 1460952000.0, "closed_at": null, "description": "", "id": 1708209, "number": 10}, {"user": "user2", "created_at": 1460697392.0, "name": "Project 2 - Feature Extraction", "due_at": 1461470400.0, "closed_at": null, "description": "", "id": 1708218, "number": 11}, {"user": "user2", "created_at": 1460697399.0, "name": "Project 2 - Predictor", "due_at": 1461816000.0, "closed_at": null, "description": "", "id": 1708219, "number": 12}, {"user": "user2", "created_at": 1460697404.0, "name": "Project 2 - Report", "due_at": 1462075200.0, "closed_at": null, "description": "", "id": 1708220, "number": 13}]